{
  "id": "gupta-post-gupta",
  "title": "भाग V: गुप्त साम्राज्य और परवर्ती काल",
  "items": [
    {
      "id": "gupta-dynasty",
      "type": "dynasty-details",
      "summary": {
        "title": "गुप्त वंश (Gupta Dynasty)",
        "period": "c. 319–550 CE",
        "founder": "श्री गुप्त",
        "capital": "पाटलिपुत्र"
      },
      "subItems": [
        "chandragupta-i",
        "samudragupta",
        "chandragupta-ii"
      ]
    },
    {
      "id": "vakataka-dynasty",
      "type": "dynasty-details",
      "summary": {
        "title": "वाकाटक वंश (Vakataka Dynasty)",
        "period": "c. 250–500 CE",
        "founder": "विंध्यशक्ति",
        "capital": "वत्सगुल्म"
      },
      "subItems": [
        "vakataka-intro"
      ]
    },
    {
      "id": "pallava-dynasty",
      "type": "dynasty-details",
      "summary": {
        "title": "पल्लव वंश (Pallava Dynasty)",
        "period": "c. 275 – 897 CE",
        "founder": "सिंहविष्णु",
        "capital": "कांचीपुरम"
      },
      "subItems": [
        "pallava-details"
      ]
    },
    {
      "id": "rai-dynasty",
      "type": "dynasty-details",
      "summary": {
        "title": "राय वंश (सिंध) (Rai Dynasty)",
        "period": "c. 489 – 632 CE",
        "founder": "राय साहसी प्रथम",
        "capital": "अरोड़"
      },
      "subItems": [
        "rai-details"
      ]
    },
    {
      "id": "western-chalukya-dynasty",
      "type": "dynasty-details",
      "summary": {
        "title": "पश्चिमी चालुक्य वंश (Western Chalukya)",
        "period": "c. 543 – 753 CE",
        "founder": "पुलकेशिन प्रथम",
        "capital": "बादामी (वातापी)"
      },
      "subItems": [
        "western-chalukya-details"
      ]
    },
    {
      "id": "maukhari-dynasty",
      "type": "dynasty-details",
      "summary": {
        "title": "मौखरि वंश (Maukhari Dynasty)",
        "period": "c. 550 – 606 CE",
        "founder": "ईशानवर्मन",
        "capital": "कन्नौज"
      },
      "subItems": [
        "maukhari-details"
      ]
    },
    {
      "id": "gauda-kingdom",
      "type": "dynasty-details",
      "summary": {
        "title": "गौड़ साम्राज्य (Gauda Kingdom)",
        "period": "c. 590 – 626 CE",
        "founder": "शशांक",
        "capital": "कर्णसुवर्ण"
      },
      "subItems": [
        "gauda-details"
      ]
    },
    {
      "id": "vardhana-dynasty-parent",
      "type": "dynasty-details",
      "summary": {
        "title": "वर्धन वंश (थानेसर) (Vardhana Dynasty)",
        "period": "c. 550–647 CE",
        "founder": "पुष्यभूति",
        "capital": "थानेसर / कन्नौज"
      },
      "subItems": [
        "vardhana-dynasty"
      ]
    }
  ]
}