{
  "id": "khizr-khan",
  "type": "king-details king-color-founder enhanced-profile",
  "summary": {
    "title": "рдЦрд┐рдЬреНрд░ рдЦрд╛рди (Khizr Khan)",
    "reign": "1414тАУ1421 CE"
  },
  "content": "<div class=\"royal-legacy-card\"><div class=\"legacy-section\"><div class=\"legacy-section-header\"><span class=\"legacy-icon\">ЁЯСС</span><h5>рд░рд╛рдЬреНрдпрд╛рд░реЛрд╣рдг: рд╕рддреНрддрд╛ рдХрд╛ рдЙрджрдп</h5></div><div class=\"legacy-section-content\"><p>рд╕реИрдпрдж рд╡рдВрд╢ рдХрд╛ рд╕рдВрд╕реНрдерд╛рдкрдХред рдЙрд╕рдиреЗ 'рд╕реБрд▓реНрддрд╛рди' рдХреА рдЙрдкрд╛рдзрд┐ рдирд╣реАрдВ рд▓реА, рдмрд▓реНрдХрд┐ рддреИрдореВрд░ рдХреЗ рдмреЗрдЯреЗ, рд╢рд╛рд╣рд░реБрдЦ рдХреЗ рдПрдХ рдбрд┐рдкреНрдЯреА рдХреЗ рд░реВрдк рдореЗрдВ рд╢рд╛рд╕рди рдХрд┐рдпрд╛ред</p><div class=\"profile-tags\"><span class=\"profile-tag\">рд░реИрдпрдд-рдП-рдЖрд▓рд╛ (Rayat-i-Ala)</span></div></div></div><div class=\"legacy-section\"><div class=\"legacy-section-header\"><span class=\"legacy-icon\">ЁЯУЬ</span><h5>рд╢рд╛рд╕рди рдФрд░ рдкреНрд░рд╢рд╛рд╕рди</h5></div><div class=\"legacy-section-content\"><p>рдЙрд╕рдХрд╛ рд╢рд╛рд╕рдирдХрд╛рд▓ рджрд┐рд▓реНрд▓реА рдХреЗ рдЖрд╕рдкрд╛рд╕ рдХреЗ рдХреНрд╖реЗрддреНрд░реЛрдВ рдкрд░ рдирд┐рдпрдВрддреНрд░рдг рдмрдирд╛рдП рд░рдЦрдиреЗ рдХреЗ рд▓рд┐рдП рдПрдХ рдирд┐рд░рдВрддрд░ рд╕рдВрдШрд░реНрд╖ рдореЗрдВ рдмреАрддрд╛ред</p></div></div></div>"
}