{
  "id": "parthians",
  "type": "king-details enhanced-profile",
  "summary": {
    "title": "इंडो-पार्थियन (Indo-Parthians)",
    "reign": "c. 19 – 226 CE"
  },
  "content": "<div class=\"royal-legacy-card\"><div class=\"legacy-section\"><div class=\"legacy-section-header\"><span class=\"legacy-icon\">⏳</span><h5>विरासत और मूल्यांकन</h5></div><div class=\"legacy-section-content\"><h6>गोंडोफर्नेस</h6><p>इस राजवंश का सबसे प्रसिद्ध शासक। ईसाई परंपरा के अनुसार, सेंट थॉमस प्रेरित उसके शासनकाल के दौरान ईसाई धर्म का प्रचार करने के लिए भारत आए थे।</p></div></div></div>",
  "reignDuration": 207,
  "empireSize": 400000
}