{
  "id": "sikandar-shah-suri",
  "type": "king-details enhanced-profile",
  "summary": {
    "title": "सिकंदर शाह सूरी (Sikandar Shah Suri)",
    "title_en": "Sikandar Shah Suri",
    "reign": "1555 CE",
    "reign_en": "1555 CE"
  },
  "reignDuration": 1,
  "empireSize": 1000000,
  "imageUrl": "images/sikandar_shah_suri.jpg",
  "content": "<div class=\"royal-legacy-card\"><div class=\"legacy-section\"><div class=\"legacy-section-header\"><span class=\"legacy-icon\">⚔️</span><h5>संघर्ष और पतन</h5></div><div class=\"legacy-section-content\"><p>वह सूर वंश का छठा शासक था (मूल नाम: अहमद खान)। उसने इब्राहिम शाह सूरी को हराकर पंजाब और दिल्ली पर अधिकार किया था।<br><strong>सरहिंद का युद्ध (1555):</strong> वह हुमायूँ और बैरम खान की मुगल सेना से सरहिंद में पराजित हुआ। इस हार ने भारत में मुगल साम्राज्य की पुनर्स्थापना की। वह शिवालिक की पहाड़ियों में भाग गया और बाद में अकबर के शासनकाल में आत्मसमर्पण कर दिया।</p></div></div></div>",
  "content_en": "<div class=\"royal-legacy-card\"><div class=\"legacy-section\"><div class=\"legacy-section-header\"><span class=\"legacy-icon\">⚔️</span><h5>Struggle and Fall</h5></div><div class=\"legacy-section-content\"><p>He was the sixth ruler of the Sur dynasty (original name: Ahmad Khan). He defeated Ibrahim Shah Suri and captured Punjab and Delhi.<br><strong>Battle of Sirhind (1555):</strong> He was defeated by the Mughal army of Humayun and Bairam Khan at Sirhind. This defeat led to the re-establishment of the Mughal Empire in India. He fled to the Shivalik hills and later surrendered during the reign of Akbar.</p></div></div></div>"
}