{
  "id": "vijayaditya",
  "type": "king-details enhanced-profile",
  "summary": {
    "title": "рд╡рд┐рдЬрдпрд╛рджрд┐рддреНрдп (Vijayaditya)",
    "reign": "c. 696тАУ733 CE"
  },
  "content": "<div class=\"royal-legacy-card\"><div class=\"legacy-section\"><div class=\"legacy-section-header\"><span class=\"legacy-icon\">ЁЯХКя╕П</span><h5>рджреАрд░реНрдШ рдФрд░ рд╢рд╛рдВрддрд┐рдкреВрд░реНрдг рд╢рд╛рд╕рди</h5></div><div class=\"legacy-section-content\"><p>рдЪрд╛рд▓реБрдХреНрдп рд╡рдВрд╢ рдХрд╛ рд╕рдмрд╕реЗ рд▓рдВрдмрд╛ рд╢рд╛рд╕рдирдХрд╛рд▓ (37 рд╡рд░реНрд╖)ред рдпрд╣ рд╕рдореГрджреНрдзрд┐ рдФрд░ рдордВрджрд┐рд░ рдирд┐рд░реНрдорд╛рдг рдХрд╛ рдХрд╛рд▓ рдерд╛ред</p></div></div><div class=\"legacy-section\"><div class=\"legacy-section-header\"><span class=\"legacy-icon\">ЁЯЫХ</span><h5>рд╡рд╛рд╕реНрддреБрдХрд▓рд╛</h5></div><div class=\"legacy-section-content\"><p>рдЗрдиреНрд╣реЛрдВрдиреЗ рдкрдЯреНрдЯрджрдХрд▓ (Pattadakal) рдореЗрдВ 'рд╕рдВрдЧрдореЗрд╢реНрд╡рд░ рдордВрджрд┐рд░' (рд╡рд┐рдЬрдпреЗрд╢реНрд╡рд░) рдХрд╛ рдирд┐рд░реНрдорд╛рдг рдХрд░рд╡рд╛рдпрд╛ред</p></div></div><div class=\"legacy-section\"><div class=\"legacy-section-header\"><span class=\"legacy-icon\">ЁЯУМ</span><h5>рдорд╣рддреНрд╡рдкреВрд░реНрдг рддрдереНрдп (Exam Points)</h5></div><div class=\"legacy-section-content\"><ul class=\"fact-list\"><li><strong>рдЙрдкрд╛рдзрд┐:</strong> рд╕рдорд╕реНрддрднреБрд╡рдирд╛рд╢реНрд░рдпред</li></ul></div></div></div>",
  "reignDuration": 37,
  "empireSize": 800000,
  "imageUrl": "images/vijayaditya.jpg"
}